napari_timelapse_processor/__init__.py
napari_timelapse_processor/_version.py
napari_timelapse_processor/frame_by_frame.py
napari_timelapse_processor/napari.yaml
napari_timelapse_processor/timelapse_converter.py
napari_timelapse_processor/_tests/__init__.py
napari_timelapse_processor/_tests/conftest.py
napari_timelapse_processor/_tests/test_frame_by_frame.py
napari_timelapse_processor/_tests/test_timelapse_converter.py
napari_timelapse_processor-0.1.1.dist-info/licenses/LICENSE
napari_timelapse_processor-0.1.1.dist-info/METADATA
napari_timelapse_processor-0.1.1.dist-info/WHEEL
napari_timelapse_processor-0.1.1.dist-info/entry_points.txt
napari_timelapse_processor-0.1.1.dist-info/top_level.txt
napari_timelapse_processor-0.1.1.dist-info/RECORD
