Metadata-Version: 2.4
Name: napari-timelapse-processor
Version: 0.1.1
Summary: meta plugin to ease processing timelapse image data
Author: Johannes Soltwedel
Author-email: johannes_richard.soltwedel@tu-dresden.de
License: 
Project-URL: Repository, https://github.com/jo-mueller/napari-timelapse-processor.git
Classifier: Development Status :: 2 - Pre-Alpha
Classifier: Framework :: napari
Classifier: Intended Audience :: Developers
Classifier: License :: OSI Approved :: BSD License
Classifier: Operating System :: OS Independent
Classifier: Programming Language :: Python
Classifier: Programming Language :: Python :: 3
Classifier: Programming Language :: Python :: 3 :: Only
Classifier: Programming Language :: Python :: 3.9
Classifier: Programming Language :: Python :: 3.10
Classifier: Programming Language :: Python :: 3.11
Classifier: Programming Language :: Python :: 3.12
Classifier: Topic :: Scientific/Engineering :: Image Processing
Requires-Python: >=3.9
License-File: LICENSE
Requires-Dist: numpy
Requires-Dist: tqdm
Requires-Dist: napari
Requires-Dist: dask
Requires-Dist: distributed
Provides-Extra: testing
Requires-Dist: tox; extra == "testing"
Requires-Dist: pytest; extra == "testing"
Requires-Dist: pytest-cov; extra == "testing"
Dynamic: license-file
